clutch_co_scraper/__init__.py
clutch_co_scraper/clutch_co_scraper/__init__.py
clutch_co_scraper/clutch_co_scraper/items.py
clutch_co_scraper/clutch_co_scraper/middlewares.py
clutch_co_scraper/clutch_co_scraper/pipelines.py
clutch_co_scraper/clutch_co_scraper/settings.py
clutch_co_scraper/clutch_co_scraper/spiders/__init__.py
clutch_co_scraper/clutch_co_scraper/spiders/main.py
clutch.co_scraper-1.0.0.dist-info/LICENSE
clutch.co_scraper-1.0.0.dist-info/METADATA
clutch.co_scraper-1.0.0.dist-info/WHEEL
clutch.co_scraper-1.0.0.dist-info/entry_points.txt
clutch.co_scraper-1.0.0.dist-info/top_level.txt
clutch.co_scraper-1.0.0.dist-info/RECORD
