Metadata-Version: 2.1
Name: clutch.co-scraper
Version: 1.0.0
Summary: clutch.co-scraper is a command-line application written in Python that scrapes and saves information about firms according to the user-defined filters.
Home-page: https://github.com/maksr137/clutch.co-scraper
Author: Maksym Remezovskyi
Author-email: maks.remezovskij1@gmail.com
License: MIT
Classifier: Programming Language :: Python :: 3
Classifier: License :: OSI Approved :: MIT License
Classifier: Operating System :: OS Independent
License-File: LICENSE
Requires-Dist: attrs (==22.1.0)
Requires-Dist: Automat (==20.2.0)
Requires-Dist: certifi (==2022.6.15)
Requires-Dist: cffi (==1.15.1)
Requires-Dist: charset-normalizer (==2.1.0)
Requires-Dist: constantly (==15.1.0)
Requires-Dist: cryptography (==37.0.4)
Requires-Dist: cssselect (==1.1.0)
Requires-Dist: et-xmlfile (==1.1.0)
Requires-Dist: fake-useragent (==0.1.11)
Requires-Dist: Faker (==13.15.1)
Requires-Dist: filelock (==3.8.0)
Requires-Dist: hyperlink (==21.0.0)
Requires-Dist: idna (==3.3)
Requires-Dist: incremental (==21.3.0)
Requires-Dist: itemadapter (==0.7.0)
Requires-Dist: itemloaders (==1.0.4)
Requires-Dist: jmespath (==1.0.1)
Requires-Dist: lxml (==4.9.1)
Requires-Dist: numpy (==1.23.1)
Requires-Dist: openpyxl (==3.0.10)
Requires-Dist: parsel (==1.6.0)
Requires-Dist: Protego (==0.2.1)
Requires-Dist: pyasn1 (==0.4.8)
Requires-Dist: pyasn1-modules (==0.2.8)
Requires-Dist: pycparser (==2.21)
Requires-Dist: PyDispatcher (==2.0.5)
Requires-Dist: pyOpenSSL (==22.0.0)
Requires-Dist: python-dateutil (==2.8.2)
Requires-Dist: queuelib (==1.6.2)
Requires-Dist: requests (==2.28.1)
Requires-Dist: requests-file (==1.5.1)
Requires-Dist: Scrapy (==2.6.2)
Requires-Dist: scrapy-fake-useragent (==1.4.4)
Requires-Dist: service-identity (==21.1.0)
Requires-Dist: six (==1.16.0)
Requires-Dist: tldextract (==3.3.1)
Requires-Dist: Twisted (==22.4.0)
Requires-Dist: twisted-iocpsupport (==1.0.2)
Requires-Dist: typing-extensions (==4.3.0)
Requires-Dist: urllib3 (==1.26.11)
Requires-Dist: w3lib (==1.22.0)
Requires-Dist: zope.interface (==5.4.0)
